runpod_ssh_setup.py
runpod_ssh_setup-1.0.1.dist-info/LICENSE
runpod_ssh_setup-1.0.1.dist-info/METADATA
runpod_ssh_setup-1.0.1.dist-info/WHEEL
runpod_ssh_setup-1.0.1.dist-info/entry_points.txt
runpod_ssh_setup-1.0.1.dist-info/RECORD
