Metadata-Version: 2.3
Name: runpod_ssh_setup
Version: 1.0.1
Summary: Simple CLI to manage SSH config entries for RunPod.
License: MIT
Keywords: ssh,config,cli,runpod,automation,setup
Author: Dominik Roblek
Requires-Python: >=3.9
Classifier: Programming Language :: Python :: 3
Classifier: Topic :: Utilities
Classifier: Topic :: System :: Systems Administration
Classifier: License :: OSI Approved :: MIT License
Classifier: Operating System :: OS Independent
Classifier: Environment :: Console
Classifier: Intended Audience :: Developers
Classifier: Intended Audience :: System Administrators
Requires-Dist: loguru
